wikidata_bot_framework/__init__.py
wikidata_bot_framework/constants.py
wikidata_bot_framework/dataclasses.py
wikidata_bot_framework/process_reason.py
wikidata_bot_framework/py.typed
wikidata_bot_framework/sentry.py
wikidata_bot_framework/transformers.py
wikidata_bot_framework/utils.py
wikidata_bot_framework-7.7.2.dist-info/LICENSE
wikidata_bot_framework-7.7.2.dist-info/METADATA
wikidata_bot_framework-7.7.2.dist-info/WHEEL
wikidata_bot_framework-7.7.2.dist-info/top_level.txt
wikidata_bot_framework-7.7.2.dist-info/zip-safe
wikidata_bot_framework-7.7.2.dist-info/RECORD
