Metadata-Version: 2.1
Name: wikidata-bot-framework
Version: 7.7.2
Summary: A framework for making Wikidata bots.
License: MIT License
Project-URL: repository, https://github.com/PythonCoderAS/wikidata-bot-framework
Classifier: Programming Language :: Python :: 3
Classifier: Programming Language :: Python :: 3 :: Only
Classifier: Programming Language :: Python :: 3.9
Classifier: Programming Language :: Python :: 3.10
Classifier: Programming Language :: Python :: 3.11
Classifier: Programming Language :: Python :: 3.12
Classifier: Programming Language :: Python :: 3.13
Classifier: Programming Language :: Python :: Implementation :: CPython
Classifier: Topic :: Software Development :: Version Control :: Git
Classifier: Development Status :: 5 - Production/Stable
Classifier: Intended Audience :: Developers
Classifier: License :: OSI Approved :: MIT License
Classifier: Natural Language :: English
Classifier: Operating System :: OS Independent
Classifier: Topic :: Software Development :: Libraries
Classifier: Topic :: Software Development :: Libraries :: Python Modules
Classifier: Typing :: Typed
Classifier: Topic :: Documentation :: Sphinx
Requires-Python: >=3.9
License-File: LICENSE
Requires-Dist: pywikibot <9
Requires-Dist: mwparserfromhell
Requires-Dist: python-dotenv
Requires-Dist: sentry-sdk
Requires-Dist: typing-extensions
Provides-Extra: docs
Requires-Dist: sphinx ; extra == 'docs'
Requires-Dist: sphinx-rtd-theme ; extra == 'docs'
Provides-Extra: lint
Requires-Dist: ruff ; extra == 'lint'
Provides-Extra: test
Requires-Dist: pytest ; extra == 'test'
